mcp_analyst/__init__.py
mcp_analyst/analyst.py
mseep_mcp_analyst-0.3.4.dist-info/METADATA
mseep_mcp_analyst-0.3.4.dist-info/WHEEL
mseep_mcp_analyst-0.3.4.dist-info/entry_points.txt
mseep_mcp_analyst-0.3.4.dist-info/top_level.txt
mseep_mcp_analyst-0.3.4.dist-info/RECORD
