Metadata-Version: 2.4
Name: mseep-mcp-analyst
Version: 0.3.4
Summary: MCP Analyst is an MCP server that empowers claude to analyze local CSV or Parquet files.
Author-email: mseep <support@skydeck.ai>
Requires-Python: >=3.13
Requires-Dist: mcp[cli]>=1.6.0
Requires-Dist: polars>=1.26.0
